{"EID":"23","CID":"1377","CATN":"Business","CATT":"18","LVLT":"5","PUBD":"2015/12/31 15:36:18","ENCODE":"80c1","VERSION":"0","ST":"会议通知","TT":"會議通知","TRE":"Meeting Notice","TRJ":"会議のお知らせ","TRK":"","Sents":{"1":{"STRE":"All members of sales department，","STRJ":"営業部各位：","STRK":"영업부 여러분:","Words":{"1":{"WID":"230001","SW":"销售部","TW":"銷售部","PY":"xiāoshòubù","EN":"sales department","JP":"販売部","KR":"","KW":"Y"},"2":{"WID":"230002","SW":"全体","TW":"全體","PY":"quántǐ","EN":"All","JP":"全体","KR":"","KW":"N"},"3":{"WID":"230003","SW":"成员","TW":"成員","PY":"chéngyuán","EN":"members","JP":"メンバー","KR":"","KW":"Y"},"4":{"WID":"230004","SW":"：","TW":"：","PY":"","EN":"","JP":"","KR":"","KW":"N"},"0":{}}},"2":{"STRE":"The meeting which is supposed to be held in 2:30 pm this 4th","STRJ":"先日、今月4日、午後2時半からの会議をお知らせしましたが、","STRK":"원래 금월 4일 오후 2 시에 예정된 회의가","Words":{"1":{"WID":"230005","SW":"原","TW":"原","PY":"yuán","EN":"primary; original","JP":"もと","KR":"","KW":"Y"},"2":{"WID":"230006","SW":"定于","TW":"定于","PY":"dìngyú","EN":"due to","JP":"に～ことにする","KR":"","KW":"Y"},"3":{"WID":"230007","SW":"本月","TW":"本月","PY":"běnyuè","EN":"this month","JP":"今月","KR":"","KW":"N"},"4":{"WID":"230008","SW":"四号","TW":"四號","PY":"sìhào","EN":"fourth","JP":"4号","KR":"","KW":"N"},"5":{"WID":"230009","SW":"下午","TW":"下午","PY":"xiàwǔ","EN":"afternoon","JP":"午後","KR":"","KW":"N"},"6":{"WID":"230010","SW":"两点半","TW":"兩點半","PY":"liǎngdiǎnbàn","EN":"2:30","JP":"２時半","KR":"","KW":"N"},"7":{"WID":"230011","SW":"的","TW":"的","PY":"de","EN":"Subordinating particle","JP":"の","KR":"","KW":"N"},"8":{"WID":"230012","SW":"会议","TW":"會議","PY":"huìyì","EN":"conference","JP":"会議","KR":"","KW":"N"},"9":{"WID":"230013","SW":"，","TW":"，","PY":"","EN":"","JP":"","KR":"","KW":"N"},"0":{}}},"3":{"STRE":"will be suspended to 2:30 pm. 7th.","STRJ":"部長が急な出張のため、今月7日、午後2時半からに変更いたします。","STRK":"부장의 임시 출장으로 인하여 금월 7일 오후 2 시에 지연됐습니다.","Words":{"1":{"WID":"230014","SW":"因","TW":"因","PY":"yīn","EN":"because of","JP":"…なので","KR":"","KW":"N"},"2":{"WID":"230015","SW":"部门","TW":"部門","PY":"bùmén","EN":"department","JP":"部門","KR":"","KW":"N"},"3":{"WID":"230016","SW":"经理","TW":"經理","PY":"jīnglǐ","EN":"manager","JP":"マネージャー","KR":"","KW":"N"},"4":{"WID":"230017","SW":"临时","TW":"臨時","PY":"línshí","EN":"temporary","JP":"臨時","KR":"","KW":"N"},"5":{"WID":"230018","SW":"出差","TW":"出差","PY":"chūchāi","EN":"on a business trip","JP":"出張する","KR":"","KW":"Y"},"6":{"WID":"230019","SW":"，","TW":"，","PY":"","EN":"","JP":"","KR":"","KW":"N"},"7":{"WID":"230020","SW":"将","TW":"將","PY":"jiāng","EN":"will","JP":"まもなく","KR":"","KW":"N"},"8":{"WID":"230021","SW":"推迟","TW":"推遲","PY":"tuīchí","EN":"put off","JP":"延期する","KR":"","KW":"Y"},"9":{"WID":"230022","SW":"到","TW":"到","PY":"dào","EN":"till","JP":"まで;（～の程度に）達する","KR":"","KW":"N"},"10":{"WID":"230023","SW":"本月","TW":"本月","PY":"běnyuè","EN":"this month","JP":"今月","KR":"","KW":"N"},"11":{"WID":"230024","SW":"七号","TW":"七號","PY":"qīhào","EN":"7th","JP":"７号","KR":"","KW":"N"},"12":{"WID":"230025","SW":"下午","TW":"下午","PY":"xiàwǔ","EN":"afternoon","JP":"午後","KR":"","KW":"N"},"13":{"WID":"230026","SW":"两点半","TW":"兩點半","PY":"liǎngdiǎnbàn","EN":"2:30","JP":"２時半","KR":"","KW":"N"},"14":{"WID":"230027","SW":"。","TW":"。","PY":"","EN":"","JP":"","KR":"","KW":"N"},"0":{}}},"4":{"STRE":"Still in the 1st meeting room on the second floor of the company.","STRJ":"場所は変わらず2階第一会議室です。","STRK":"","Words":{"1":{"WID":"230028","SW":"地点","TW":"地點","PY":"dìdiǎn","EN":"location","JP":"場所","KR":"","KW":"N"},"2":{"WID":"230029","SW":"仍","TW":"仍","PY":"réng","EN":"still","JP":"依然として","KR":"","KW":"N"},"3":{"WID":"230030","SW":"是","TW":"是","PY":"shì","EN":"be","JP":"だ，である","KR":"","KW":"N"},"4":{"WID":"230031","SW":"公司","TW":"公司","PY":"gōngsī","EN":"company","JP":"会社","KR":"","KW":"N"},"5":{"WID":"230032","SW":"二楼","TW":"二樓","PY":"èrlóu","EN":"second floor","JP":"２階","KR":"","KW":"Y"},"6":{"WID":"230033","SW":"第一","TW":"第一","PY":"dìyī","EN":"first","JP":"一番目の","KR":"","KW":"N"},"7":{"WID":"230034","SW":"会议室","TW":"會議室","PY":"huìyìshì","EN":"meeting room","JP":"会議室","KR":"","KW":"Y"},"8":{"WID":"230035","SW":"。","TW":"。","PY":"","EN":"","JP":"","KR":"","KW":"N"},"0":{}}},"5":{"STRE":"Please pass this message to each other and make sure to attend the meeting on time.","STRJ":"変更につきましての周知にご協力をいただき、時間厳守でお願いいたします。","STRK":"서로 전해주시고 반드시 시간을 맞추셔서 참가해주시길 바랍니다.","Words":{"1":{"WID":"230036","SW":"请","TW":"請","PY":"qǐng","EN":"please","JP":"てください","KR":"","KW":"N"},"2":{"WID":"230037","SW":"大家","TW":"大家","PY":"dàjiā","EN":"everyone","JP":"みんな","KR":"","KW":"N"},"3":{"WID":"230038","SW":"相互","TW":"相互","PY":"xiānghù","EN":"each other","JP":"相互に","KR":"","KW":"N"},"4":{"WID":"230039","SW":"转告","TW":"轉告","PY":"zhuǎngào","EN":"pass on ; send word","JP":"伝え","KR":"","KW":"N"},"5":{"WID":"230040","SW":"，","TW":"，","PY":"","EN":"","JP":"","KR":"","KW":"N"},"6":{"WID":"230041","SW":"务必","TW":"務必","PY":"wùbì","EN":"be sure to","JP":"必ず","KR":"","KW":"N"},"7":{"WID":"230042","SW":"准时","TW":"準時","PY":"zhǔnshí","EN":"on time","JP":"時間通りに","KR":"","KW":"Y"},"8":{"WID":"230043","SW":"参加","TW":"參加","PY":"cānjiā","EN":"attend","JP":"参加する","KR":"","KW":"Y"},"9":{"WID":"230044","SW":"。","TW":"。","PY":"","EN":"","JP":"","KR":"","KW":"N"},"0":{}}},"0":{}}}