{
	"又": {
		"py": "yòu",
		"mn": [
			[
				"adv",
				"lại (biểu thị lặp lại hoặc tiếp tục) | vừa...vừa.... | lại; lại thêm; lại còn (biểu thị tăng thêm) | nhưng; lại (biểu thị chuyển ý) | còn; thêm (biểu thị bổ sung) | thêm; cộng; với | vừa... lại; vừa... vừa (biểu thị hai sự việc có mâu thuẫn) | đâu (biểu thị nhấn mạnh)"
			]
		]
	},
	"到": {
		"py": "dào",
		"mn": [
			[
				"v",
				"đi; đến; đi đến | đến; tới | đến; được (dùng làm bổ ngữ chỉ kết quả)"
			],
			[
				"prep",
				"đến"
			],
			[
				"adj",
				"chu đáo; ân cần"
			],
			[
				"n",
				"họ Đáo"
			]
		]
	},
	"了": {
		"py": "le",
		"mn": [
			[
				"part",
				"đã; rồi (động tác được thực hiện) | đã; rồi (tính chất trạng thái có sự thay đổi) | thôi; rồi; nữa (biểu thị sự thôi thúc hoặc khuyên ngăn) | quá; rồi (dùng trong câu cảm thán)"
			]
		]
	},
	"我": {
		"py": "wǒ",
		"mn": [
			[
				"pro",
				"tôi; ta; tao; tớ; mình (tự xưng bản thân mình) | chúng ta; chúng tôi | mình; tôi (người nói tự gọi mình) | một người nào đó"
			]
		]
	},
	"都": {
		"py": "dōu",
		"mn": [
			[
				"adv",
				"đều; cả; hoàn toàn; toàn bộ | vì; tại; do; đều; cũng vì; đều tại | cũng; thậm chí | đã; cũng đã"
			]
		]
	},
	"出去": {
		"py": "chūqù",
		"mn": [
			[
				"v",
				"ra; ra ngoài"
			]
		]
	},
	"旅行": {
		"py": "lǚxíng",
		"mn": [
			[
				"v",
				"lữ hành; du lịch (động từ bất cập vật)"
			],
			[
				"n",
				"chuyến du lịch; du lịch"
			]
		]
	},
	"但": {
		"py": "dàn",
		"mn": [
			[
				"conj",
				"nhưng; nhưng mà; tuy nhiên"
			],
			[
				"adv",
				"chỉ; chỉ cần"
			]
		]
	},
	"今年": {
		"py": "jīnnián",
		"mn": [
			[
				"n, time",
				"năm nay"
			]
		]
	},
	"没": {
		"py": "méi",
		"mn": [
			[
				"v",
				"không; không có (sở hữu) | không có (tồn tại) | không | không bằng | không tới; không đến; chưa đến"
			],
			[
				"adv",
				"chưa; chưa từng"
			]
		]
	},
	"玩儿": {
		"py": "wánr",
		"mn": [
			[
				"v",
				"chơi; giải trí; vui chơi; chơi đùa"
			]
		]
	},
	"因为": {
		"py": "yīnwèi",
		"mn": [
			[
				"prep",
				"bởi vì; bởi rằng; vì; số là; tại đâu; tại vì; vì rằng"
			],
			[
				"conj",
				"vì; do; bởi vì"
			]
		]
	},
	"是": {
		"py": "shì",
		"mn": [
			[
				"v",
				"là | là; đó; ấy; đấy | đúng; thích hợp | cho là; cho rằng; cho là đúng | phải; vâng; được | hay; hay là | chính là | quả là; quả thật | hễ; phàm; bất cứ"
			],
			[
				"adj",
				"đúng; phải; hợp lý"
			],
			[
				"n",
				"sự đúng; điều phải; điều đúng đắn | họ Thị"
			],
			[
				"pro",
				"đây; này; vậy"
			]
		]
	},
	"旅游": {
		"py": "lǚyóu",
		"mn": [
			[
				"v",
				"du ngoạn; du lịch"
			]
		]
	},
	"的": {
		"py": "de",
		"mn": [
			[
				"part",
				"của (chỉ sở hữu) | miêu tả thêm cho trung tâm ngữ | thay thế cho người hoặc vật đã đề cập trước đó | nhấn mạnh hành động, sự việc đã thực hiện (thời gian, địa điểm, phương thức) | diễn tả khẳng định (đứng cuối câu kể) | biểu thị rằng ai đó đã đạt được chức vụ hoặc địa vị nhất định | chỉ rõ đối tượng nào đó | vân vân; các loại như; v.v. | kết hợp với động từ phía trước biểu thị ai đó là đối tượng của động tác"
			]
		]
	},
	"不管": {
		"py": "bùguǎn",
		"mn": [
			[
				"conj",
				"cho dù; bất kể; bất luận; chẳng kể; mặc dù"
			],
			[
				"v",
				"mặc; bỏ mặc; mặc kệ; bỏ liều; bất chấp; kệ; mặc bay"
			]
		]
	},
	"坐": {
		"py": "zuò",
		"mn": [
			[
				"v",
				"ngồi | ngồi; đi; đáp (phương tiện giao thông) | quay lưng; quay lưng về (hướng nào đó) | đặt; để (xoong, nồi, ấm lên bếp) | giật; lún; giật hậu | ra quả; kết quả; có quả | bị tội; định tội; kết tội; buộc tội | bị; mắc (bệnh tật) | nắm giữ; quản lý; chủ trì;  chịu trách nhiệm"
			],
			[
				"prep",
				"vì; bởi vì"
			],
			[
				"n",
				"chỗ ngồi; ghế ngồi | họ Tọa"
			],
			[
				"adv",
				"tự dưng; vô cớ; vô duyên vô cớ"
			],
			[
				"adj",
				"chắc; mẩy; mọng nước"
			]
		]
	},
	"飞机": {
		"py": "fēijī",
		"mn": [
			[
				"n",
				"máy bay; phi cơ; tàu bay"
			]
		]
	},
	"人": {
		"py": "rén",
		"mn": [
			[
				"n",
				"người; con người | loại người | thành niên; người trưởng thành | người khác | mỗi người; người bình thường | người tài; nhân tài | phẩm chất; tính cách; danh dự | chỉ thân thể con người"
			]
		]
	},
	"很": {
		"py": "hěn",
		"mn": [
			[
				"adv",
				"rất; lắm; quá; hết sức"
			]
		]
	},
	"多": {
		"py": "duō",
		"mn": [
			[
				"adj",
				"đa; nhiều (quá mức; không cần thiết) | hơn nhiều; rất nhiều (mức chênh lệch) | nhiều; lắm"
			],
			[
				"v",
				"dư; thừa; thừa ra; dư ra | thêm"
			],
			[
				"adv",
				"bao nhiêu; thế nào; đến mức nào  (dùng trong câu hỏi) | bao nhiêu; thế nào; bấy nhiêu; đến đâu; cỡ nào | rất; lắm; quá; vô cùng; quả thật; biết mấy (dừng trong câu cảm thán) | đa số; hầu hết; phần nhiều; phần lớn; đa phần"
			],
			[
				"numb",
				"hơn; ngoài"
			],
			[
				"n",
				"họ Đa"
			]
		]
	},
	"机票": {
		"py": "jīpiào",
		"mn": [
			[
				"n",
				"vé máy bay"
			]
		]
	},
	"一般": {
		"py": "yībān",
		"mn": [
			[
				"adj",
				"như; giống nhau; như nhau | trung bình; bình thường; trình độ không cao"
			],
			[
				"adv",
				"thường; thông thường"
			]
		]
	},
	"没有": {
		"py": "méiyǒu",
		"mn": [
			[
				"v",
				"không có (sở hữu) | không (tồn tại) | không bằng | không đủ; không tới; không đến"
			],
			[
				"adv",
				"chưa | chưa từng; chưa hề"
			]
		]
	},
	"折扣": {
		"py": "zhékòu",
		"mn": [
			[
				"n",
				"chiết khấu; giảm giá | thiếu hụt; giảm bớt"
			]
		]
	},
	"住": {
		"py": "zhù",
		"mn": [
			[
				"v",
				"ở; sống; trọ; cư trú | dừng; ngưng; dừng lại | được; nổi; đủ sức; đảm nhiệm được; chịu đựng được | chắc; chặt"
			]
		]
	},
	"也": {
		"py": "yě",
		"mn": [
			[
				"adv",
				"cũng (biểu thị giống nhau) | cũng (dùng để nhấn mạnh) | cũng; vẫn (bắt buộc) | cũng (nhẹ nhàng, tế nhị) | cũng (thế nào cũng được)"
			],
			[
				"part",
				"(biểu thị ngữ khí tạm dừng trong câu) | vậy (biểu thị khẳng định hoặc nghi vấn)"
			]
		]
	},
	"要": {
		"py": "yào",
		"mn": [
			[
				"v",
				"muốn; hi vọng | cần có; muốn có | xin; đòi; yêu cầu | nhờ; thỉnh cầu | cần (bao nhiêu) | phải; nên; cần phải | sắp; sẽ | chắc; có lẽ | muốn; cần"
			],
			[
				"adj",
				"quan trọng; cần thiết"
			],
			[
				"n",
				"nội dung chính; nội dung quan trọng"
			],
			[
				"conj",
				"nếu; nếu như | hoặc là"
			]
		]
	},
	"比": {
		"py": "bǐ",
		"mn": [
			[
				"prep",
				"hơn; so; so với"
			],
			[
				"v",
				"sát; kề; kề sát; dựa sát | cấu kết; dựa vào; nương tựa; phụ thuộc | đọ; so sánh; so đo | như; tương tự; sánh bằng; ngang với | chia (toán học) | tỉ số | noi theo; phỏng theo; mô phỏng | ví; so; ví von | ra dấu; ra hiệu (diễn tả bằng điệu bộ) | nhắm vào; nhằm vào; hướng vào"
			],
			[
				"n",
				"tỷ lệ | nước Bỉ"
			],
			[
				"adv",
				"gần đây"
			]
		]
	},
	"平时": {
		"py": "píngshí",
		"mn": [
			[
				"time, n",
				"bình thường; lúc thường; ngày thường | thời bình"
			]
		]
	},
	"贵": {
		"py": "guì",
		"mn": [
			[
				"adj",
				"đắt; mắc | quý; quý giá | cao quý; sang trọng; quý tộc; địa vị cao | quý (xưng hô lễ phép, tôn trọng)"
			],
			[
				"n",
				"Quý Châu | họ Quý"
			],
			[
				"v",
				"coi trọng; xem trọng; quý trọng"
			]
		]
	},
	"里": {
		"py": "lǐ",
		"mn": [
			[
				"n",
				"bên trong; phía trong | lót (bên trong, mặt trái của áo hoặc chăn) | xóm; làng | quê hương | trong; nội bộ | nơi; chỗ | họ Lí"
			],
			[
				"measure",
				"dặm (đơn vị đo chiều dài, bằng 1/2 km)"
			]
		]
	},
	"玩": {
		"py": "wán",
		"mn": [
			[
				"v",
				"đùa; chơi; nghịch; chơi đùa | chơi (thể thao) | giở; giở trò (thủ đoạn, mánh khoé) | khinh; xem nhẹ; đùa giỡn | ngắm; ngắm nhìn; thưởng ngoạn | cảm nhận; nghiền ngẫm; suy ngẫm"
			],
			[
				"n",
				"đồ; đồ vật; đồ chơi | họ Ngoạn"
			]
		]
	},
	"起": {
		"py": "qǐ",
		"mn": [
			[
				"v",
				"dậy (đứng dậy, thức dậy) | rời; xê; rời khỏi; cất cánh | hất lên; nảy lên; bung lên; lên xuống | nổi; lên (bọc nước, mục ngứa, rôm sảy) | nhổ; nhấc; lôi; bốc | xảy ra | khởi thảo; soạn thảo; đặt tên | thành lập; xây dựng | lĩnh; nhận | bắt đầu từ (ai, ở đâu, khi nào) | bắt đầu một hành động nào đó (dùng sau động từ biểu thị sự bắt đầu) | nhấc lên; xách lên;  ngẩng lên (hướng lên trên) | nổi; được (dùng sau động từ, biểu thị đủ lực hoặc không đủ lực làm việc gì) | đến; tới; về (dùng sau động từ biểu thị động tác liên quan tới người hoặc sự vật nào đó) | bắt đầu (dùng sau động từ biểu thị sự bắt đầu) | lại (dùng sau một động từ để gắn kết cái gì đó lại với nhau hoặc hợp lại)"
			],
			[
				"measure",
				"kiện; cái; vụ (tai nạn, sự cố) | tốp; bầy; loạt; đám; nhóm"
			],
			[
				"prep",
				"từ (chỉ thời gian hoặc địa điểm) | đi qua (giới từ, dùng trước từ chỉ nơi chốn, chỉ những địa điểm đã qua)"
			]
		]
	},
	"来": {
		"py": "lái",
		"mn": [
			[
				"v",
				"đến; tới (từ chỗ khác đến chỗ người nói) | tới; đến (dùng sau động từ, biểu thị động tác hướng về phía lời nói) | xảy đến; xảy ra (vấn đề, sự tình) | để (dùng giữa kết cấu động từ hoặc kết cấu giữa động từ và giới từ, biểu thị thành phần trước là phương pháp, phương hướng, thành phần sau là mục đích) | hãy; để (dùng trước một động từ khác, biểu thị làm một việc gì đó) | đánh; mở; làm (dùng thay cho một số động tác) | hợp; được"
			],
			[
				"part",
				"khoảng; chừng (đứng sau số từ hoặc số lượng từ để biểu thị số ước lượng) | dùng làm từ đệm trong thơ ca; tục ngữ hoặc lời rao hàng | ấy nhỉ | là (dùng sau số từ như \"一\"\"二\" \"三\", liệt kê lý do)"
			],
			[
				"n",
				"tới nay; từ trước tới nay (một thời điểm nhất định trong quá khứ cho đến hiện tại) | họ Lai"
			],
			[
				"adj",
				"tương lai; sau này"
			]
		]
	},
	"比较": {
		"py": "bǐjiào",
		"mn": [
			[
				"v",
				"so với; hơn | so sánh; so đo; sánh cùng"
			],
			[
				"adv",
				"tương đối; khá; khá là"
			]
		]
	},
	"在": {
		"py": "zài",
		"mn": [
			[
				"v",
				"sống; tồn tại; sinh tồn | ở (biểu thị người hoặc vị trí của sự vật) | tại; tại chức; đang giữ | do; quyết định bởi | thuộc; tham gia"
			],
			[
				"adv",
				"đang (làm gì đó)"
			],
			[
				"prep",
				"đang, ở, vào (ở đâu, thời gian nào, điều kiện nào)"
			]
		]
	},
	"家": {
		"py": "jiā",
		"mn": [
			[
				"n",
				"nhà; gia đình | nhà; nơi ở; chỗ ở | nhà; dân; tay | nhà; chuyên gia; chuyên viên | nhà; gia; phái | nhà; gia (lời nói khiêm tốn, xưng hô với người trên bậc của mình) | bên; đối thủ; đối phương | dân tộc | nhà; gia (gia đình hoặc cá nhân có mối quan hệ) | họ Gia"
			],
			[
				"adj",
				"nuôi quen; đã thuần phục (động vật)"
			],
			[
				"measure",
				"ngôi; hiệu; tiệm; quán; nhà (dùng chỉ nhà hoặc xí nghiệp)"
			]
		]
	},
	"好好": {
		"py": "hǎohǎo",
		"mn": [
			[
				"adv",
				"quá"
			]
		]
	},
	"做": {
		"py": "zuò",
		"mn": [
			[
				"v",
				"chế tạo | viết; sáng tác | làm; làm việc; thực hiện | làm; tổ chức; chúc mừng | đảm nhiệm; trở thành | làm; dùng làm; sử dụng làm | trở thành; kết thành; tạo thành (quan hệ) | giả vờ; giả trang"
			]
		]
	},
	"饭": {
		"py": "fàn",
		"mn": [
			[
				"n",
				"cơm | bữa | công việc; nguồn thu nhập; cách kiếm sống"
			],
			[
				"v",
				"ăn; ăm cơm; dùng bữa"
			]
		]
	},
	"过": {
		"py": "guò",
		"mn": [
			[
				"v",
				"qua; đi qua; chảy qua | qua; hơn; vượt qua | quá; hơn; vượt (phạm vi hoặc giới hạn) | trải qua (một khoảng thời gian) | ăn; đón | chuyển; chuyền; đưa qua | qua; cho qua (xử lý, giải quyết) | đi thăm; đến thăm; viếng thăm | chết; qua đời | lây; truyền nhiễm | vượt; hơn | sống | xem qua; hồi tưởng"
			],
			[
				"adv",
				"rất; quá"
			],
			[
				"measure",
				"lần; lượt"
			],
			[
				"n",
				"lỗi; sai lầm; sai sót"
			]
		]
	},
	"一": {
		"py": "yī",
		"mn": [
			[
				"numb",
				"một; số một | đồng nhất; như nhau; cùng nhau | cả; đầy | một lòng; chuyên nhất; chuyên tâm | mỗi; mỗi một | một; cái một | cái khác; một cái khác"
			],
			[
				"adv",
				"một chút; một lát | vừa; hễ; mỗi khi; cứ mỗi lần | đột ngột; bất ngờ"
			],
			[
				"n",
				"nhất (một cấp độ trong âm nhạc Trung Quốc)"
			],
			[
				"part",
				"vậy (dùng trước từ nào đó để tăng thêm ngữ khí)"
			]
		]
	},
	"个": {
		"py": "gè",
		"mn": [
			[
				"measure",
				"cái; con; quả; trái; người | khoảng (dùng trước số ước lượng) | một; một chút | dùng giữa động từ và bổ ngữ | một (dùng giữa \"没\" (méi), \"有\" (yǒu) và một số động từ hoặc tính từ, mang chức năng nhấn mạnh)"
			],
			[
				"part",
				"là hậu tố dùng sau ''些'' | là hậu tố dùng sau thời gian"
			],
			[
				"adj",
				"cá nhân; đơn độc; riêng biệt; riêng lẻ"
			],
			[
				"n",
				"chiều cao; kích thước"
			]
		]
	},
	"感觉": {
		"py": "gǎnjué",
		"mn": [
			[
				"v",
				"cảm thấy; cho rằng"
			],
			[
				"n",
				"cảm giác"
			]
		]
	},
	"挺": {
		"py": "tǐng",
		"mn": [
			[
				"adv",
				"rất; lắm"
			],
			[
				"v",
				"ưỡn; ngửa | gắng gượng; cố gắng | ủng hộ"
			],
			[
				"measure",
				"khẩu; cây"
			],
			[
				"adj",
				"thẳng; ngay | vượt trội; đặc sắc; xuất sắc; kiệt xuất"
			]
		]
	},
	"不": {
		"py": "bù",
		"mn": [
			[
				"adv",
				"không; chẳng; chả | bất; phi; vô; không (thêm vào trước danh từ, ngữ danh từ, để tạo thành hình dung từ) | không (dùng ở cuối câu, biểu thị câu hỏi) | không cần; không phải; đừng | không (dùng để trả lời)"
			]
		]
	},
	"错": {
		"py": "cuò",
		"mn": [
			[
				"v",
				"nghiền; nghiến; mài; xay; giũa; ma sát; chà xát | nhường; tránh; lỡ; bỏ qua | dời; giãn; xê xích; xê dịch (thời gian) | mài; đánh bóng (ngọc, ngọc thạch) | thếp; nạm; khảm (vàng, bạc) | rối; chéo nhau; hỗn tạp; lộn xộn; đan vào nhau"
			],
			[
				"n",
				"sai lầm; sai sót; lỗi sai | đá mài (để mài ngọc)"
			],
			[
				"adj",
				"lộn xộn; bừa bộn; rối loạn | sai; nhầm; không đúng | tồi; tệ; kém; sai; thối; ươn (dùng ở dạng phủ định)"
			]
		]
	}
}