{
	"你": {
		"py": "nǐ",
		"mn": [
			[
				"pro",
				"bạn; anh; chị; ông; bà; ngươi; mày; mi; cậu... | các bạn; các anh; các chị; các bà; các ông; chúng mày (có thể dùng với số nhiều) | bạn (chỉ bất kỳ ai, bao gồm cả người nói) | bạn; cậu (chỉ sự tham gia của nhiều người)"
			],
			[
				"n",
				"họ Nhĩ"
			]
		]
	},
	"是": {
		"py": "shì",
		"mn": [
			[
				"v",
				"là | là; đó; ấy; đấy | đúng; thích hợp | cho là; cho rằng; cho là đúng | phải; vâng; được | hay; hay là | chính là | quả là; quả thật | hễ; phàm; bất cứ"
			],
			[
				"adj",
				"đúng; phải; hợp lý"
			],
			[
				"n",
				"sự đúng; điều phải; điều đúng đắn | họ Thị"
			],
			[
				"pro",
				"đây; này; vậy"
			]
		]
	},
	"大学生": {
		"py": "dàxuéshēng",
		"mn": [
			[
				"n",
				"sinh viên; sinh viên đại học"
			]
		]
	},
	"吗": {
		"py": "ma",
		"mn": [
			[
				"part",
				"không; ư; à (dùng ở cuối câu để hỏi) | ấy à; ấy ư (dùng ở cuối câu, ngắt nghỉ để nhấn mạnh) | ư; à (biểu thị phản vấn)"
			]
		]
	},
	"对": {
		"py": "duì",
		"mn": [
			[
				"prep",
				"về; với; đối với"
			],
			[
				"measure",
				"đôi; cặp"
			],
			[
				"adj",
				"đúng; chính xác | đối diện; đối địch; bên kia"
			],
			[
				"n",
				"câu đối | cặp đôi (quan hệ hợp tác)"
			],
			[
				"v",
				"trả lời; đáp lời; đối đáp | đối đãi; đối xử; đối phó | hướng về; nhằm vào | đối; khớp; khép | so sánh; đối chiếu | chỉnh; điều chỉnh; sửa đổi | pha | chia đôi; chia hai | xứng; hợp; vừa; tương ứng; phù hợp"
			],
			[
				"adv",
				"đối diện; lẫn nhau; qua lại"
			]
		]
	},
	"我": {
		"py": "wǒ",
		"mn": [
			[
				"pro",
				"tôi; ta; tao; tớ; mình (tự xưng bản thân mình) | chúng ta; chúng tôi | mình; tôi (người nói tự gọi mình) | một người nào đó"
			]
		]
	},
	"在": {
		"py": "zài",
		"mn": [
			[
				"v",
				"sống; tồn tại; sinh tồn | ở (biểu thị người hoặc vị trí của sự vật) | tại; tại chức; đang giữ | do; quyết định bởi | thuộc; tham gia"
			],
			[
				"adv",
				"đang (làm gì đó)"
			],
			[
				"prep",
				"đang, ở, vào (ở đâu, thời gian nào, điều kiện nào)"
			]
		]
	},
	"北京大学": {
		"py": "běijīngdàxué",
		"mn": [
			[
				"n",
				"Đại học bắc kinh"
			]
		]
	},
	"读书": {
		"py": "dúshū",
		"mn": [
			[
				"v, sv",
				"đọc sách; học bài | đi học"
			]
		]
	},
	"现在": {
		"py": "xiànzài",
		"mn": [
			[
				"n, time",
				"hiện tại; hiện nay; bây giờ; hiện giờ; lúc này"
			]
		]
	},
	"几": {
		"py": "jǐ",
		"mn": [
			[
				"numb",
				"mấy (hỏi số lượng bao nhiêu) | mấy; vài (biểu thị một số không xác định từ hai đến chín) | mấy; vài (thay thế con số nhất định) | ngày nào"
			]
		]
	},
	"年级": {
		"py": "niánjí",
		"mn": [
			[
				"n",
				"lớp; khóa; năm học"
			]
		]
	},
	"研究生": {
		"py": "yánjiūshēng",
		"mn": [
			[
				"n",
				"nghiên cứu sinh"
			]
		]
	},
	"什么": {
		"py": "shénme",
		"mn": [
			[
				"pro",
				"gì; cái gì | gì; nào (dùng trước danh từ, hỏi người hoặc sự vật) | gì đó (Đại từ phiếm chỉ) | gì; nấy; thế (hai từ''什么''đứng trước sau bổ sung cho nhau, thì cái trước quyết định cái sau) | thể hiện sự trách móc | cái gì (biểu thị phủ định)"
			],
			[
				"intj",
				"cái gì; cái quái gì (thể hiện sự kinh ngạc hoặc bất mãn) | hả; á (thể hiện không đồng ý một câu nói nào đó của đối phương)"
			]
		]
	},
	"专业": {
		"py": "zhuānyè",
		"mn": [
			[
				"n",
				"môn; bộ môn; chuyên ngành"
			],
			[
				"adj",
				"chuyên nghiệp"
			]
		]
	},
	"的": {
		"py": "de",
		"mn": [
			[
				"part",
				"của (chỉ sở hữu) | miêu tả thêm cho trung tâm ngữ | thay thế cho người hoặc vật đã đề cập trước đó | nhấn mạnh hành động, sự việc đã thực hiện (thời gian, địa điểm, phương thức) | diễn tả khẳng định (đứng cuối câu kể) | biểu thị rằng ai đó đã đạt được chức vụ hoặc địa vị nhất định | chỉ rõ đối tượng nào đó | vân vân; các loại như; v.v. | kết hợp với động từ phía trước biểu thị ai đó là đối tượng của động tác"
			]
		]
	},
	"法律": {
		"py": "fǎlǜ",
		"mn": [
			[
				"n",
				"luật; pháp luật; luật pháp"
			]
		]
	}
}