{"EID":"710","CID":"1488","CATN":"Language","CATT":"6","LVLT":"6","PUBD":"2/26/2018 12:00:00 AM","ENCODE":"4ae2","VERSION":"0","ST":"道歉","TT":"道歉","TRE":"Apologize","TRJ":"謝る","TRK":"","Sents":{"1":{"STRE":"A: Lily，I am sorry! ","STRJ":"A: 李麗、ごめん！","STRK":"A: 이리. 미안해.","Words":{"1":{"WID":"7100001","SW":"A","TW":"A","PY":"","EN":"","JP":"","KR":"","KW":"N"},"2":{"WID":"7100002","SW":":","TW":":","PY":"","EN":"","JP":"","KR":"","KW":"N"},"3":{"WID":"7100003","SW":"李丽","TW":"李麗","PY":"lǐlì","EN":"Lily","JP":"李麗","KR":"","KW":"N"},"4":{"WID":"7100004","SW":"，","TW":"，","PY":"","EN":"","JP":"","KR":"","KW":"N"},"5":{"WID":"7100005","SW":"对不起","TW":"對不起","PY":"duìbùqǐ","EN":"I‘m sorry","JP":"すみません;ごめんなさい","KR":"","KW":"Y"},"6":{"WID":"7100006","SW":"！","TW":"！","PY":"","EN":"","JP":"","KR":"","KW":"N"},"0":{}}},"2":{"STRE":"A: Don't be mad， It's all my fault!","STRJ":"A: 怒らないで、僕が悪かったよ！","STRK":"A: 화를 내지 마. 다 내 잘 못이야.","Words":{"1":{"WID":"7100007","SW":"A","TW":"A","PY":"","EN":"","JP":"","KR":"","KW":"N"},"2":{"WID":"7100008","SW":":","TW":":","PY":"","EN":"","JP":"","KR":"","KW":"N"},"3":{"WID":"7100009","SW":"别生气","TW":"別生氣","PY":"biéshēngqì","EN":"Don't be mad","JP":"怒らないで","KR":"","KW":"Y"},"4":{"WID":"7100010","SW":"了","TW":"了","PY":"le","EN":"The dynamic particle 了（le）signifies 1)the occurrence or completion of an action or event，or 2)the emergence of a situation.3）modal particle (used to complete the sentence.","JP":"動作や状態の完了","KR":"","KW":"N"},"5":{"WID":"7100011","SW":"，","TW":"，","PY":"","EN":"","JP":"","KR":"","KW":"N"},"6":{"WID":"7100012","SW":"都","TW":"都","PY":"dōu","EN":"All","JP":"すべて;全部;みな","KR":"","KW":"N"},"7":{"WID":"7100013","SW":"是","TW":"是","PY":"shì","EN":"Be","JP":"は","KR":"","KW":"N"},"8":{"WID":"7100014","SW":"我","TW":"我","PY":"wǒ","EN":"I","JP":"私","KR":"","KW":"N"},"9":{"WID":"7100015","SW":"的","TW":"的","PY":"de","EN":"Subordinating particle","JP":"の","KR":"","KW":"N"},"10":{"WID":"7100016","SW":"错","TW":"錯","PY":"cuò","EN":"Wrong","JP":"間違いました","KR":"","KW":"Y"},"11":{"WID":"7100017","SW":"！","TW":"！","PY":"","EN":"","JP":"","KR":"","KW":"N"},"0":{}}},"3":{"STRE":"B: I don't think it works for me. ","STRJ":"B: 謝ったら済むの？","STRK":"B: 미안하다고 말 하면 괜찮은 거야?","Words":{"1":{"WID":"7100018","SW":"B","TW":"B","PY":"","EN":"","JP":"","KR":"","KW":"N"},"2":{"WID":"7100019","SW":":","TW":":","PY":"","EN":"","JP":"","KR":"","KW":"N"},"3":{"WID":"7100020","SW":"说","TW":"說","PY":"shuō","EN":"Say","JP":"言います","KR":"","KW":"N"},"4":{"WID":"7100021","SW":"对不起","TW":"對不起","PY":"duìbùqǐ","EN":"I‘m sorry","JP":"すみません;ごめんなさい","KR":"","KW":"Y"},"5":{"WID":"7100022","SW":"就","TW":"就","PY":"jiù","EN":"Then，right after","JP":"就く;について;…ば…する","KR":"","KW":"N"},"6":{"WID":"7100023","SW":"没事","TW":"沒事","PY":"méishì","EN":"Nothing","JP":"大丈夫;なんのこともない","KR":"","KW":"N"},"7":{"WID":"7100024","SW":"了","TW":"了","PY":"le","EN":"The dynamic particle 了（le）signifies 1)the occurrence or completion of an action or event，or 2)the emergence of a situation.3）modal particle (used to complete the sentence.","JP":"動作や状態の完了","KR":"","KW":"N"},"8":{"WID":"7100025","SW":"？","TW":"？","PY":"","EN":"","JP":"","KR":"","KW":"N"},"0":{}}},"4":{"STRE":"B: You've left me waiting for you infront of the movie theater for an hour!","STRJ":"B: 私一人、映画館の入り口で1時間も立たせて！","STRK":"B: 나 혼자 영화관 문앞에 1 시간을 기다리라고 했어.","Words":{"1":{"WID":"7100026","SW":"B","TW":"B","PY":"","EN":"","JP":"","KR":"","KW":"N"},"2":{"WID":"7100027","SW":":","TW":":","PY":"","EN":"","JP":"","KR":"","KW":"N"},"3":{"WID":"7100028","SW":"你","TW":"你","PY":"nǐ","EN":"You","JP":"あなた","KR":"","KW":"N"},"4":{"WID":"7100029","SW":"让","TW":"讓","PY":"ràng","EN":"Let，make","JP":"させます","KR":"","KW":"N"},"5":{"WID":"7100030","SW":"我","TW":"我","PY":"wǒ","EN":"I","JP":"私","KR":"","KW":"N"},"6":{"WID":"7100031","SW":"一个人","TW":"一個人","PY":"yīgèrén","EN":"By oneself","JP":"一人","KR":"","KW":"N"},"7":{"WID":"7100032","SW":"在","TW":"在","PY":"zài","EN":"At，in","JP":"ある;いる","KR":"","KW":"N"},"8":{"WID":"7100033","SW":"电影院","TW":"電影院","PY":"diànyǐngyuàn","EN":"Cinema","JP":"映画館","KR":"","KW":"N"},"9":{"WID":"7100034","SW":"门口","TW":"門口","PY":"ménkǒu","EN":"Door","JP":"玄関","KR":"","KW":"N"},"10":{"WID":"7100035","SW":"站","TW":"站","PY":"zhàn","EN":"Stand","JP":"駅","KR":"","KW":"Y"},"11":{"WID":"7100036","SW":"了","TW":"了","PY":"le","EN":"The dynamic particle 了（le）signifies 1)the occurrence or completion of an action or event，or 2)the emergence of a situation.3）modal particle (used to complete the sentence.","JP":"動作や状態の完了","KR":"","KW":"N"},"12":{"WID":"7100037","SW":"一个小时","TW":"一個小時","PY":"yīgèxiǎoshí","EN":"One hour","JP":"一時間","KR":"","KW":"N"},"13":{"WID":"7100038","SW":"！","TW":"！","PY":"","EN":"","JP":"","KR":"","KW":"N"},"0":{}}},"5":{"STRE":"A: I left home half an hour ahead of time， ","STRJ":"A: 30分前には出たんだよ。","STRK":"A: 나 30 분 이리 출발했는데.","Words":{"1":{"WID":"7100039","SW":"A","TW":"A","PY":"","EN":"","JP":"","KR":"","KW":"N"},"2":{"WID":"7100040","SW":":","TW":":","PY":"","EN":"","JP":"","KR":"","KW":"N"},"3":{"WID":"7100041","SW":"我","TW":"我","PY":"wǒ","EN":"I","JP":"私","KR":"","KW":"N"},"4":{"WID":"7100042","SW":"提前","TW":"提前","PY":"tíqián","EN":"In advance","JP":"早めに","KR":"","KW":"N"},"5":{"WID":"7100043","SW":"半个小时","TW":"半個小時","PY":"bàngèxiǎoshí","EN":"Half an hour","JP":"３０分","KR":"","KW":"N"},"6":{"WID":"7100044","SW":"就","TW":"就","PY":"jiù","EN":"Then，right after","JP":"就く;について;…ば…する","KR":"","KW":"N"},"7":{"WID":"7100045","SW":"出发","TW":"出發","PY":"chūfā","EN":"Start off","JP":"出発","KR":"","KW":"N"},"8":{"WID":"7100046","SW":"了","TW":"了","PY":"le","EN":"The dynamic particle 了（le）signifies 1)the occurrence or completion of an action or event，or 2)the emergence of a situation.3）modal particle (used to complete the sentence.","JP":"動作や状態の完了","KR":"","KW":"N"},"9":{"WID":"7100047","SW":"，","TW":"，","PY":"","EN":"","JP":"","KR":"","KW":"N"},"0":{}}},"6":{"STRE":"A: But I ran into a traffic jam. There was nothing I could do to it.","STRJ":"A: でも道が混んでて。どうすることもできなかったんだよ。","STRK":"A: 결국 길에서 차가 막혀서 나도 어쩔 수 없잖아.","Words":{"1":{"WID":"7100048","SW":"A","TW":"A","PY":"","EN":"","JP":"","KR":"","KW":"N"},"2":{"WID":"7100049","SW":":","TW":":","PY":"","EN":"","JP":"","KR":"","KW":"N"},"3":{"WID":"7100050","SW":"结果","TW":"結果","PY":"jiéguǒ","EN":"As a result","JP":"結果","KR":"","KW":"N"},"4":{"WID":"7100051","SW":"路上","TW":"路上","PY":"lùshàng","EN":"On the road","JP":"途中","KR":"","KW":"Y"},"5":{"WID":"7100052","SW":"堵车","TW":"堵車","PY":"dǔchē","EN":"Traffic jam","JP":"交通渋滞","KR":"","KW":"Y"},"6":{"WID":"7100053","SW":"，","TW":"，","PY":"","EN":"","JP":"","KR":"","KW":"N"},"7":{"WID":"7100054","SW":"我","TW":"我","PY":"wǒ","EN":"I","JP":"私","KR":"","KW":"N"},"8":{"WID":"7100055","SW":"也","TW":"也","PY":"yě","EN":"Also","JP":"も","KR":"","KW":"N"},"9":{"WID":"7100056","SW":"没办法","TW":"沒辦法","PY":"méibànfǎ","EN":"No way out; have no choice but","JP":"しょうがない","KR":"","KW":"N"},"10":{"WID":"7100057","SW":"啊","TW":"啊","PY":"a","EN":"Final particle，modal particle","JP":"ああ","KR":"","KW":"N"},"11":{"WID":"7100058","SW":"！","TW":"！","PY":"","EN":"","JP":"","KR":"","KW":"N"},"0":{}}},"7":{"STRE":"B: If there was a traffic jam， why can't you call me?","STRJ":"B: 道が混んでるなら、電話くらいしてくれてもいいじゃない？","STRK":"B: 너 차가 막혀서 왜 미리 전화를 안 해줘?","Words":{"1":{"WID":"7100059","SW":"B","TW":"B","PY":"","EN":"","JP":"","KR":"","KW":"N"},"2":{"WID":"7100060","SW":":","TW":":","PY":"","EN":"","JP":"","KR":"","KW":"N"},"3":{"WID":"7100061","SW":"你","TW":"你","PY":"nǐ","EN":"You","JP":"あなた","KR":"","KW":"N"},"4":{"WID":"7100062","SW":"堵车","TW":"堵車","PY":"dǔchē","EN":"Traffic jam","JP":"交通渋滞","KR":"","KW":"Y"},"5":{"WID":"7100063","SW":"，","TW":"，","PY":"","EN":"","JP":"","KR":"","KW":"N"},"6":{"WID":"7100064","SW":"为什么","TW":"為什么","PY":"wèishénme","EN":"Why","JP":"なぜ","KR":"","KW":"N"},"7":{"WID":"7100065","SW":"不能","TW":"不能","PY":"bùnéng","EN":"Can not","JP":"することはできません","KR":"","KW":"N"},"8":{"WID":"7100066","SW":"给","TW":"給","PY":"gěi","EN":"For，to","JP":"与えます;くれます","KR":"","KW":"N"},"9":{"WID":"7100067","SW":"我","TW":"我","PY":"wǒ","EN":"I","JP":"私","KR":"","KW":"N"},"10":{"WID":"7100068","SW":"打","TW":"打","PY":"dǎ","EN":"打dǎ电话diànhuà，ring up; call (up)","JP":"（電話を）かける","KR":"","KW":"Y"},"11":{"WID":"7100069","SW":"个","TW":"個","PY":"gè","EN":"Measure word","JP":"個;最も広く用いられる量詞である","KR":"","KW":"N"},"12":{"WID":"7100070","SW":"电话","TW":"電話","PY":"diànhuà","EN":"Telephone","JP":"電話","KR":"","KW":"Y"},"13":{"WID":"7100071","SW":"？","TW":"？","PY":"","EN":"","JP":"","KR":"","KW":"N"},"0":{}}},"8":{"STRE":"A: I planned to， ","STRJ":"A: 僕だって電話しようとしたんだ、","STRK":"A: 원래 전화를 하려고 했는데.","Words":{"1":{"WID":"7100072","SW":"A","TW":"A","PY":"","EN":"","JP":"","KR":"","KW":"N"},"2":{"WID":"7100073","SW":":","TW":":","PY":"","EN":"","JP":"","KR":"","KW":"N"},"3":{"WID":"7100074","SW":"我","TW":"我","PY":"wǒ","EN":"I","JP":"私","KR":"","KW":"N"},"4":{"WID":"7100075","SW":"本来","TW":"本來","PY":"běnlái","EN":"Originally，at first","JP":"もともと","KR":"","KW":"N"},"5":{"WID":"7100076","SW":"要","TW":"要","PY":"yào","EN":"Want","JP":"欲しい","KR":"","KW":"N"},"6":{"WID":"7100077","SW":"给","TW":"給","PY":"gěi","EN":"For，to","JP":"与えます;くれます","KR":"","KW":"N"},"7":{"WID":"7100078","SW":"你","TW":"你","PY":"nǐ","EN":"You","JP":"あなた","KR":"","KW":"N"},"8":{"WID":"7100079","SW":"打","TW":"打","PY":"dǎ","EN":"打dǎ电话diànhuà，ring up; call (up)","JP":"（電話を）かける","KR":"","KW":"Y"},"9":{"WID":"7100080","SW":"电话","TW":"電話","PY":"diànhuà","EN":"Telephone","JP":"電話","KR":"","KW":"Y"},"10":{"WID":"7100081","SW":"的","TW":"的","PY":"de","EN":"Particle","JP":"の","KR":"","KW":"N"},"11":{"WID":"7100082","SW":"，","TW":"，","PY":"","EN":"","JP":"","KR":"","KW":"N"},"0":{}}},"9":{"STRE":"A: But unfortunately my mobile phone died. ","STRJ":"A: でもあいにく携帯は電池切れで。","STRK":"A: 폰 배터리가 떨어졌어 그래.","Words":{"1":{"WID":"7100083","SW":"A","TW":"A","PY":"","EN":"","JP":"","KR":"","KW":"N"},"2":{"WID":"7100084","SW":":","TW":":","PY":"","EN":"","JP":"","KR":"","KW":"N"},"3":{"WID":"7100085","SW":"可","TW":"可","PY":"kě","EN":"Spotlight the following opinion","JP":"することができます","KR":"","KW":"N"},"4":{"WID":"7100086","SW":"不巧","TW":"不巧","PY":"bùqiǎo","EN":"Unfortunately","JP":"あいにく","KR":"","KW":"N"},"5":{"WID":"7100087","SW":"的","TW":"的","PY":"de","EN":"Subordinating particle","JP":"の","KR":"","KW":"N"},"6":{"WID":"7100088","SW":"是","TW":"是","PY":"shì","EN":"Be","JP":"は","KR":"","KW":"N"},"7":{"WID":"7100089","SW":"，","TW":"，","PY":"","EN":"","JP":"","KR":"","KW":"N"},"8":{"WID":"7100090","SW":"手机","TW":"手機","PY":"shǒujī","EN":"Telephone","JP":"電話","KR":"","KW":"N"},"9":{"WID":"7100091","SW":"没","TW":"沒","PY":"méi","EN":"Not","JP":"ありません","KR":"","KW":"N"},"10":{"WID":"7100092","SW":"电","TW":"電","PY":"diàn","EN":"Electric","JP":"電気;電流","KR":"","KW":"N"},"11":{"WID":"7100093","SW":"了","TW":"了","PY":"le","EN":"The dynamic particle 了（le）signifies 1)the occurrence or completion of an action or event，or 2)the emergence of a situation.3）modal particle (used to complete the sentence.","JP":"動作や状態の完了","KR":"","KW":"N"},"12":{"WID":"7100094","SW":"。","TW":"。","PY":"","EN":"","JP":"","KR":"","KW":"N"},"0":{}}},"10":{"STRE":"A: I was worried， but I couldn't do anything.","STRJ":"A: 僕だって焦ってたけど、どうすることもできなかったんだ！","STRK":"A: 나도 급하지만 어쩔 수 없는 거야.","Words":{"1":{"WID":"7100095","SW":"A","TW":"A","PY":"","EN":"","JP":"","KR":"","KW":"N"},"2":{"WID":"7100096","SW":":","TW":":","PY":"","EN":"","JP":"","KR":"","KW":"N"},"3":{"WID":"7100097","SW":"我","TW":"我","PY":"wǒ","EN":"I","JP":"私","KR":"","KW":"N"},"4":{"WID":"7100098","SW":"也","TW":"也","PY":"yě","EN":"Also","JP":"も","KR":"","KW":"N"},"5":{"WID":"7100099","SW":"是","TW":"是","PY":"shì","EN":"Be","JP":"は","KR":"","KW":"N"},"6":{"WID":"7100100","SW":"干着急","TW":"干著急","PY":"gānzhāojí","EN":"Be anxious but unable to do anything","JP":"ただ気をもむばかり","KR":"","KW":"N"},"7":{"WID":"7100101","SW":"没办法","TW":"沒辦法","PY":"méibànfǎ","EN":"No way out; have no choice but","JP":"しょうがない","KR":"","KW":"N"},"8":{"WID":"7100102","SW":"啊","TW":"啊","PY":"a","EN":"Final particle，modal particle","JP":"ああ","KR":"","KW":"N"},"9":{"WID":"7100103","SW":"！","TW":"！","PY":"","EN":"","JP":"","KR":"","KW":"N"},"0":{}}},"11":{"STRE":"B: These are all excuses!","STRJ":"B: 言い訳！言い訳ばっかり！","STRK":"B: 핑계. 다 핑계야.","Words":{"1":{"WID":"7100104","SW":"B","TW":"B","PY":"","EN":"","JP":"","KR":"","KW":"N"},"2":{"WID":"7100105","SW":":","TW":":","PY":"","EN":"","JP":"","KR":"","KW":"N"},"3":{"WID":"7100106","SW":"借口","TW":"借口","PY":"jièkǒu","EN":"Excuse","JP":"口実","KR":"","KW":"N"},"4":{"WID":"7100107","SW":"！","TW":"！","PY":"","EN":"","JP":"","KR":"","KW":"N"},"5":{"WID":"7100108","SW":"都","TW":"都","PY":"dōu","EN":"All","JP":"すべて;全部;みな","KR":"","KW":"N"},"6":{"WID":"7100109","SW":"是","TW":"是","PY":"shì","EN":"Be","JP":"は","KR":"","KW":"N"},"7":{"WID":"7100110","SW":"借口","TW":"借口","PY":"jièkǒu","EN":"Excuse","JP":"口実","KR":"","KW":"N"},"8":{"WID":"7100111","SW":"！","TW":"！","PY":"","EN":"","JP":"","KR":"","KW":"N"},"0":{}}},"12":{"STRE":"A: Don't be mad!  I'll take you to Quanjude restaurant ","STRJ":"A: 怒らないで！怒らないでくれよ！あとで全聚德おごるからさ。","STRK":"A: 화 내지 마. 화 내지 마. 이따가 전취덕을 사 줄게.","Words":{"1":{"WID":"7100112","SW":"A","TW":"A","PY":"","EN":"","JP":"","KR":"","KW":"N"},"2":{"WID":"7100113","SW":":","TW":":","PY":"","EN":"","JP":"","KR":"","KW":"N"},"3":{"WID":"7100114","SW":"别生气","TW":"別生氣","PY":"biéshēngqì","EN":"Don't be mad","JP":"怒らない","KR":"","KW":"Y"},"4":{"WID":"7100115","SW":"了","TW":"了","PY":"le","EN":"The dynamic particle 了（le）signifies 1)the occurrence or completion of an action or event，or 2)the emergence of a situation.3）modal particle (used to complete the sentence.","JP":"動作や状態の完了","KR":"","KW":"N"},"5":{"WID":"7100116","SW":"，","TW":"，","PY":"","EN":"","JP":"","KR":"","KW":"N"},"6":{"WID":"7100117","SW":"别生气","TW":"別生氣","PY":"biéshēngqì","EN":"Don't be mad","JP":"怒らない","KR":"","KW":"Y"},"7":{"WID":"7100118","SW":"了","TW":"了","PY":"le","EN":"The dynamic particle 了（le）signifies 1)the occurrence or completion of an action or event，or 2)the emergence of a situation.3）modal particle (used to complete the sentence.","JP":"動作や状態の完了","KR":"","KW":"N"},"8":{"WID":"7100119","SW":"！","TW":"！","PY":"","EN":"","JP":"","KR":"","KW":"N"},"9":{"WID":"7100120","SW":"一会儿","TW":"一會兒","PY":"yīhuìr","EN":"For a while","JP":"しばらく","KR":"","KW":"N"},"10":{"WID":"7100121","SW":"我","TW":"我","PY":"wǒ","EN":"I","JP":"私","KR":"","KW":"N"},"11":{"WID":"7100122","SW":"请","TW":"請","PY":"qǐng","EN":"Please，(polite form of request)，to treat or to invite somebody","JP":"お願いする","KR":"","KW":"N"},"12":{"WID":"7100123","SW":"你","TW":"你","PY":"nǐ","EN":"You","JP":"あなた","KR":"","KW":"N"},"13":{"WID":"7100124","SW":"吃","TW":"吃","PY":"chī","EN":"Eat","JP":"食べます","KR":"","KW":"N"},"14":{"WID":"7100125","SW":"全聚德","TW":"全聚德","PY":"quánjùdé","EN":"Peking duck","JP":"全聚徳、北京ダックの店の名前","KR":"","KW":"N"},"15":{"WID":"7100126","SW":"，","TW":"，","PY":"","EN":"","JP":"","KR":"","KW":"N"},"0":{}}},"13":{"STRE":"A: And go shopping after meal， ok?","STRJ":"A: そのあとウインドウショッピングとか君に付き合うよ、それでもだめ？","STRK":"A: 그리고 쇼핑도 같이 해 주면 안 돼?","Words":{"1":{"WID":"7100127","SW":"A","TW":"A","PY":"","EN":"","JP":"","KR":"","KW":"N"},"2":{"WID":"7100128","SW":":","TW":":","PY":"","EN":"","JP":"","KR":"","KW":"N"},"3":{"WID":"7100129","SW":"然后","TW":"然后","PY":"ránhòu","EN":"Then","JP":"そして","KR":"","KW":"N"},"4":{"WID":"7100130","SW":"陪","TW":"陪","PY":"péi","EN":"Accompany","JP":"付き添う","KR":"","KW":"N"},"5":{"WID":"7100131","SW":"你","TW":"你","PY":"nǐ","EN":"You","JP":"あなた","KR":"","KW":"N"},"6":{"WID":"7100132","SW":"逛街","TW":"逛街","PY":"guàngjiē","EN":"Shopping","JP":"買物","KR":"","KW":"N"},"7":{"WID":"7100133","SW":"还","TW":"還","PY":"hái","EN":"Emphasize the following content","JP":"まだ","KR":"","KW":"N"},"8":{"WID":"7100134","SW":"不行","TW":"不行","PY":"bùxíng","EN":"No","JP":"ダメ","KR":"","KW":"N"},"9":{"WID":"7100135","SW":"吗","TW":"嗎","PY":"ma","EN":"Final particle，question particle","JP":"文末で問いかけを表す","KR":"","KW":"N"},"10":{"WID":"7100136","SW":"？","TW":"？","PY":"","EN":"","JP":"","KR":"","KW":"N"},"0":{}}},"14":{"STRE":"B: Really? You'll take me for shopping?","STRJ":"B: ほんと？私と街を歩いてくれるの？","STRK":"B: 정말? 쇼핑을 해 줄 거야?","Words":{"1":{"WID":"7100137","SW":"B","TW":"B","PY":"","EN":"","JP":"","KR":"","KW":"N"},"2":{"WID":"7100138","SW":":","TW":":","PY":"","EN":"","JP":"","KR":"","KW":"N"},"3":{"WID":"7100139","SW":"真的","TW":"真的","PY":"zhēnde","EN":"Really","JP":"本当に","KR":"","KW":"N"},"4":{"WID":"7100140","SW":"？","TW":"？","PY":"","EN":"","JP":"","KR":"","KW":"N"},"5":{"WID":"7100141","SW":"你","TW":"你","PY":"nǐ","EN":"You","JP":"あなた","KR":"","KW":"N"},"6":{"WID":"7100142","SW":"陪","TW":"陪","PY":"péi","EN":"Accompany","JP":"付き添う","KR":"","KW":"N"},"7":{"WID":"7100143","SW":"我","TW":"我","PY":"wǒ","EN":"I","JP":"私","KR":"","KW":"N"},"8":{"WID":"7100144","SW":"逛街","TW":"逛街","PY":"guàngjiē","EN":"Shopping","JP":"買物","KR":"","KW":"N"},"9":{"WID":"7100145","SW":"？","TW":"？","PY":"","EN":"","JP":"","KR":"","KW":"N"},"0":{}}},"15":{"STRE":"A: Of course， I mean what I say.","STRJ":"A: もちろんさ、男に二言はない！","STRK":"A: 당연하지. 대장부 일언천금이야.","Words":{"1":{"WID":"7100146","SW":"A","TW":"A","PY":"","EN":"","JP":"","KR":"","KW":"N"},"2":{"WID":"7100147","SW":":","TW":":","PY":"","EN":"","JP":"","KR":"","KW":"N"},"3":{"WID":"7100148","SW":"当然","TW":"當然","PY":"dāngrán","EN":"Of course","JP":"もちろん","KR":"","KW":"N"},"4":{"WID":"7100149","SW":"，","TW":"，","PY":"","EN":"","JP":"","KR":"","KW":"N"},"5":{"WID":"7100150","SW":"大丈夫","TW":"大丈夫","PY":"dàzhàngfu","EN":"True man","JP":"大丈夫","KR":"","KW":"N"},"6":{"WID":"7100151","SW":"一言九鼎","TW":"一言九鼎","PY":"yīyánjiǔdǐng","EN":"One word is as heavy as nine tripods.","JP":"一語九鼎;国を左右するほど重みのある貴重な一言","KR":"","KW":"N"},"7":{"WID":"7100152","SW":"！","TW":"！","PY":"","EN":"","JP":"","KR":"","KW":"N"},"0":{}}},"16":{"STRE":"B: All right， let's have a meal first and we will have the strength to go shopping.","STRJ":"B: わかったわ、じゃあ先にご飯を食べに行きましょう。しっかり食べてパワーをためて街歩きしましょ！","STRK":"B: 그래. 그러면 우리 먼저 밥을 먹자. 배가 불러야 쇼핑을 하는 힘이 있을 수 있다.","Words":{"1":{"WID":"7100153","SW":"B","TW":"B","PY":"","EN":"","JP":"","KR":"","KW":"N"},"2":{"WID":"7100154","SW":":","TW":":","PY":"","EN":"","JP":"","KR":"","KW":"N"},"3":{"WID":"7100155","SW":"好吧","TW":"好吧","PY":"hǎoba","EN":"Okay","JP":"いいでしょう","KR":"","KW":"N"},"4":{"WID":"7100156","SW":"，","TW":"，","PY":"","EN":"","JP":"","KR":"","KW":"N"},"5":{"WID":"7100157","SW":"那","TW":"那","PY":"nà","EN":"Then，in that case","JP":"その","KR":"","KW":"N"},"6":{"WID":"7100158","SW":"我们","TW":"我們","PY":"wǒmen","EN":"We","JP":"私たち;我々","KR":"","KW":"N"},"7":{"WID":"7100159","SW":"先","TW":"先","PY":"xiān","EN":"First","JP":"先","KR":"","KW":"N"},"8":{"WID":"7100160","SW":"吃饭","TW":"吃飯","PY":"chīfàn","EN":"Eat","JP":"食事をとる","KR":"","KW":"N"},"9":{"WID":"7100161","SW":"去","TW":"去","PY":"qù","EN":"Verb， indicating the verb of motion away from the speaker","JP":"行きます","KR":"","KW":"N"},"10":{"WID":"7100162","SW":"，","TW":"，","PY":"","EN":"","JP":"","KR":"","KW":"N"},"11":{"WID":"7100163","SW":"吃","TW":"吃","PY":"chī","EN":"Eat","JP":"食べます","KR":"","KW":"N"},"12":{"WID":"7100164","SW":"饱","TW":"飽","PY":"bǎo","EN":"Full","JP":"お腹がいっぱい","KR":"","KW":"N"},"13":{"WID":"7100165","SW":"饭","TW":"飯","PY":"fàn","EN":"Rice","JP":"ライス;ごはん","KR":"","KW":"N"},"14":{"WID":"7100166","SW":"有","TW":"有","PY":"yǒu","EN":"Have","JP":"ある;いる;持つ","KR":"","KW":"N"},"15":{"WID":"7100167","SW":"力气","TW":"力氣","PY":"lìqì","EN":"Strength，effort","JP":"力","KR":"","KW":"N"},"16":{"WID":"7100168","SW":"逛街","TW":"逛街","PY":"guàngjiē","EN":"Shopping","JP":"買物","KR":"","KW":"N"},"17":{"WID":"7100169","SW":"！","TW":"！","PY":"","EN":"","JP":"","KR":"","KW":"N"},"0":{}}},"17":{"STRE":"A: Oh mine! finally you smiled.","STRJ":"A: やれやれ、やっと笑ってくれた！","STRK":"A: 아이고. 드디어 웃었어.","Words":{"1":{"WID":"7100170","SW":"A","TW":"A","PY":"","EN":"","JP":"","KR":"","KW":"N"},"2":{"WID":"7100171","SW":":","TW":":","PY":"","EN":"","JP":"","KR":"","KW":"N"},"3":{"WID":"7100172","SW":"哎呀","TW":"哎呀","PY":"āiyā","EN":"Oh","JP":"ああ","KR":"","KW":"N"},"4":{"WID":"7100173","SW":"妈呀","TW":"媽呀","PY":"māya","EN":"My god","JP":"あら","KR":"","KW":"N"},"5":{"WID":"7100174","SW":"，","TW":"，","PY":"","EN":"","JP":"","KR":"","KW":"N"},"6":{"WID":"7100175","SW":"你","TW":"你","PY":"nǐ","EN":"You","JP":"あなた","KR":"","KW":"N"},"7":{"WID":"7100176","SW":"终于","TW":"終于","PY":"zhōngyú","EN":"Finally","JP":"やっと;とうとう;ようやく","KR":"","KW":"N"},"8":{"WID":"7100177","SW":"笑","TW":"笑","PY":"xiào","EN":"Smile","JP":"笑い","KR":"","KW":"N"},"9":{"WID":"7100178","SW":"了","TW":"了","PY":"le","EN":"The dynamic particle 了（le）signifies 1)the occurrence or completion of an action or event，or 2)the emergence of a situation.3）modal particle (used to complete the sentence.","JP":"動作や状態の完了","KR":"","KW":"N"},"10":{"WID":"7100179","SW":"！","TW":"！","PY":"","EN":"","JP":"","KR":"","KW":"N"},"0":{}}},"0":{}}}