{"EID":"570","CID":"2024","CATN":"Relationship","CATT":"17","LVLT":"3","PUBD":"10/13/2017 12:00:00 AM","ENCODE":"cea6","VERSION":"0","ST":"我可以坐在这儿吗？","TT":"我可以坐在這兒嗎？","TRE":"May I sit down here?","TRJ":"ここに座ってもいいですか","TRK":"","Sents":{"1":{"STRE":"Lily: Excuse me，may I sit down here?","STRJ":"李麗：すみません、ここに座ってもいいですか","STRK":"실례하지만 저 여기 앉아도 돼요?","Words":{"1":{"WID":"5700001","SW":"李丽","TW":"李麗","PY":"lǐlì","EN":"Lily","JP":"李麗","KR":"","KW":"N"},"2":{"WID":"5700002","SW":"：","TW":"：","PY":"","EN":"","JP":"","KR":"","KW":"N"},"3":{"WID":"5700003","SW":"请问","TW":"請問","PY":"qǐngwèn","EN":"Excuse me","JP":"すみません","KR":"","KW":"N"},"4":{"WID":"5700004","SW":"，","TW":"，","PY":"","EN":"","JP":"","KR":"","KW":"N"},"5":{"WID":"5700005","SW":"我","TW":"我","PY":"wǒ","EN":"I","JP":"私","KR":"","KW":"N"},"6":{"WID":"5700006","SW":"可以","TW":"可以","PY":"kěyǐ","EN":"Can，may","JP":"いい","KR":"","KW":"Y"},"7":{"WID":"5700007","SW":"坐","TW":"坐","PY":"zuò","EN":"Sit","JP":"座る","KR":"","KW":"Y"},"8":{"WID":"5700008","SW":"在","TW":"在","PY":"zài","EN":"At","JP":"に","KR":"","KW":"N"},"9":{"WID":"5700009","SW":"这儿","TW":"這兒","PY":"zhèr","EN":"Here","JP":"ここ","KR":"","KW":"N"},"10":{"WID":"5700010","SW":"吗","TW":"嗎","PY":"ma","EN":"Final particle，question particle","JP":"疑問を表す","KR":"","KW":"N"},"11":{"WID":"5700011","SW":"？","TW":"？","PY":"","EN":"","JP":"","KR":"","KW":"N"},"0":{}}},"2":{"STRE":"Passenger: Of course.","STRJ":"乗客：いいですよ。","STRK":"당연히 돼요.","Words":{"1":{"WID":"5700012","SW":"乘客","TW":"乘客","PY":"chéngkè","EN":"Passenger","JP":"乗客","KR":"","KW":"N"},"2":{"WID":"5700013","SW":"：","TW":"：","PY":"","EN":"","JP":"","KR":"","KW":"N"},"3":{"WID":"5700014","SW":"当然","TW":"當然","PY":"dāngrán","EN":"Of course","JP":"もちろん","KR":"","KW":"Y"},"4":{"WID":"5700015","SW":"可以","TW":"可以","PY":"kěyǐ","EN":"Can","JP":"いい","KR":"","KW":"Y"},"5":{"WID":"5700016","SW":"。","TW":"。","PY":"","EN":"","JP":"","KR":"","KW":"N"},"0":{}}},"3":{"STRE":"Lily: Thanks!","STRJ":"李麗：ありがとうございます。","STRK":"감사합니다.","Words":{"1":{"WID":"5700017","SW":"李丽","TW":"李麗","PY":"lǐlì","EN":"Lily","JP":"李麗","KR":"","KW":"N"},"2":{"WID":"5700018","SW":"：","TW":"：","PY":"","EN":"","JP":"","KR":"","KW":"N"},"3":{"WID":"5700019","SW":"谢谢","TW":"謝謝","PY":"xièxiè","EN":"Thanks","JP":"ありがとう","KR":"","KW":"Y"},"4":{"WID":"5700020","SW":"！","TW":"！","PY":"","EN":"","JP":"","KR":"","KW":"N"},"0":{}}},"0":{}}}